srtranslator/__init__.py
srtranslator/__main__.py
srtranslator/ass_file.py
srtranslator/srt_file.py
srtranslator/util.py
srtranslator/translators/__init__.py
srtranslator/translators/base.py
srtranslator/translators/deepl_api.py
srtranslator/translators/deepl_scrap.py
srtranslator/translators/deeplx.py
srtranslator/translators/pydeeplx.py
srtranslator/translators/selenium_utils.py
srtranslator/translators/translatepy.py
srtranslator_bariskeser-0.0.13.dist-info/LICENSE.md
srtranslator_bariskeser-0.0.13.dist-info/METADATA
srtranslator_bariskeser-0.0.13.dist-info/WHEEL
srtranslator_bariskeser-0.0.13.dist-info/top_level.txt
srtranslator_bariskeser-0.0.13.dist-info/RECORD
