Metadata-Version: 2.1
Name: srtranslator-bariskeser
Version: 0.0.13
Summary: Özel bir çevirmen kullanarak bir .SRT dosyasını çevirin
Home-page: https://github.com/barkeser2002/srtranslator-bariskeser
Author: bariskeser2002
Author-email: info@bariskeser.com
License: FREE
Keywords: python,srt,diller,çevirmen,altyazılar
Requires-Python: >=3.6
License-File: LICENSE.md
Requires-Dist: deepl==1.19.1
Requires-Dist: free_proxy==1.1.2
Requires-Dist: pyass==0.1.4
Requires-Dist: translatepy==2.3
Requires-Dist: selenium==4.7.2
Requires-Dist: srt==3.5.3
Requires-Dist: PyDeepLX==1.0.7
Requires-Dist: webdriverdownloader==1.1.0.4
Requires-Dist: httpx
